{"cameraMode":{"drawMode":0,"name":"Shaded","section":"Shading Mode"},"sceneLighting":true,"audioPlay":false,"sceneViewState":{"m_AlwaysRefresh":false,"showFog":true,"showSkybox":true,"showFlares":true,"showImageEffects":true,"showParticleSystems":true,"showVisualEffectGraphs":true,"m_FxEnabled":true},"in2DMode":false,"pivot":{"x":1.1991214752197266,"y":-18.749238967895509,"z":38.471595764160159},"rotation":{"x":-0.26672717928886416,"y":0.046819765120744708,"z":-0.013006516732275486,"w":-0.9625990986824036},"size":49.1888427734375,"orthographic":false}